url2bib/__init__.py
url2bib/core.py
url2bib/venues.py
url2bib/version.py
url2bib/bin/url2bib
url2bib-0.4.6.data/scripts/url2bib
url2bib-0.4.6.dist-info/licenses/LICENSE
url2bib-0.4.6.dist-info/METADATA
url2bib-0.4.6.dist-info/WHEEL
url2bib-0.4.6.dist-info/top_level.txt
url2bib-0.4.6.dist-info/RECORD
