Metadata-Version: 2.4
Name: url2bib
Version: 0.4.6
Summary: Convert URLs to BibTeX entries, with support for DOI and ISBN extraction
Home-page: https://github.com/notpaulmartin/url2bib
Author: Paul Martin
Author-email: p@ulmartin.com
License: GNU General Public License v3 (GPLv3)
Keywords: bibtex,science,scientific-journals,crossref,doi,isbn
Classifier: Development Status :: 4 - Beta
Classifier: License :: OSI Approved :: GNU General Public License v3 (GPLv3)
Classifier: Intended Audience :: Science/Research
Classifier: Programming Language :: Python :: 3
Classifier: Programming Language :: Python :: 3.6
Classifier: Programming Language :: Python :: 3.7
Classifier: Programming Language :: Python :: 3.8
Classifier: Programming Language :: Python :: 3.9
Classifier: Topic :: Text Processing :: Markup :: LaTeX
Requires-Python: >=3.6
License-File: LICENSE
Requires-Dist: requests>=2.25.0
Requires-Dist: bibtexparser>=1.2.0
Requires-Dist: urllib3>=1.26.0
Requires-Dist: beautifulsoup4>=4.9.0
Dynamic: author
Dynamic: author-email
Dynamic: classifier
Dynamic: description
Dynamic: description-content-type
Dynamic: home-page
Dynamic: keywords
Dynamic: license
Dynamic: license-file
Dynamic: requires-dist
Dynamic: requires-python
Dynamic: summary
